{"created": 1783830240.8247433, "duration": 63.710150957107544, "exitcode": 1, "root": "/home/luis/GitHub/beduality/terracotta", "environment": {}, "summary": {"passed": 11, "failed": 2, "total": 13, "collected": 13}, "collectors": [{"nodeid": "", "outcome": "passed", "result": [{"nodeid": "scripts/test_release_smoke.py", "type": "Module"}]}, {"nodeid": "scripts/test_release_smoke.py", "outcome": "passed", "result": [{"nodeid": "scripts/test_release_smoke.py::test_github_release_exists", "type": "Function", "lineno": 64}, {"nodeid": "scripts/test_release_smoke.py::test_maven_central_artifacts", "type": "Function", "lineno": 84}, {"nodeid": "scripts/test_release_smoke.py::test_jar_contents", "type": "Function", "lineno": 111}, {"nodeid": "scripts/test_release_smoke.py::test_public_sites", "type": "Function", "lineno": 144}, {"nodeid": "scripts/test_release_smoke.py::test_github_release_body_matches_changelog", "type": "Function", "lineno": 160}, {"nodeid": "scripts/test_release_smoke.py::test_source_tree_version_strings", "type": "Function", "lineno": 199}, {"nodeid": "scripts/test_release_smoke.py::test_gpg_signature_files", "type": "Function", "lineno": 222}, {"nodeid": "scripts/test_release_smoke.py::test_javadoc_jars_not_empty", "type": "Function", "lineno": 272}, {"nodeid": "scripts/test_release_smoke.py::test_docs_sub_pages", "type": "Function", "lineno": 300}, {"nodeid": "scripts/test_release_smoke.py::test_docs_version_reflected", "type": "Function", "lineno": 319}, {"nodeid": "scripts/test_release_smoke.py::test_build_from_tag", "type": "Function", "lineno": 331}, {"nodeid": "scripts/test_release_smoke.py::test_gradle_plugin_e2e", "type": "Function", "lineno": 343}, {"nodeid": "scripts/test_release_smoke.py::test_sdk_e2e", "type": "Function", "lineno": 393}]}], "tests": [{"nodeid": "scripts/test_release_smoke.py::test_github_release_exists", "lineno": 64, "outcome": "passed", "keywords": ["test_github_release_exists", "test_release_smoke.py", "scripts", "terracotta", ""], "setup": {"duration": 0.0002565630002209218, "outcome": "passed"}, "call": {"duration": 0.5709272859994599, "outcome": "passed"}, "teardown": {"duration": 0.00025793099939619424, "outcome": "passed"}}, {"nodeid": "scripts/test_release_smoke.py::test_maven_central_artifacts", "lineno": 84, "outcome": "passed", "keywords": ["test_maven_central_artifacts", "test_release_smoke.py", "scripts", "terracotta", ""], "setup": {"duration": 0.0003228129999115481, "outcome": "passed"}, "call": {"duration": 6.079673242999888, "outcome": "passed"}, "teardown": {"duration": 0.0003848750002362067, "outcome": "passed"}}, {"nodeid": "scripts/test_release_smoke.py::test_jar_contents", "lineno": 111, "outcome": "passed", "keywords": ["test_jar_contents", "test_release_smoke.py", "scripts", "terracotta", ""], "setup": {"duration": 0.0006706550002490985, "outcome": "passed"}, "call": {"duration": 0.1772335990008287, "outcome": "passed"}, "teardown": {"duration": 0.00024009300068428274, "outcome": "passed"}}, {"nodeid": "scripts/test_release_smoke.py::test_public_sites", "lineno": 144, "outcome": "passed", "keywords": ["test_public_sites", "test_release_smoke.py", "scripts", "terracotta", ""], "setup": {"duration": 0.0003877460003423039, "outcome": "passed"}, "call": {"duration": 3.069059040999491, "outcome": "passed"}, "teardown": {"duration": 0.00011159000041516265, "outcome": "passed"}}, {"nodeid": "scripts/test_release_smoke.py::test_github_release_body_matches_changelog", "lineno": 160, "outcome": "passed", "keywords": ["test_github_release_body_matches_changelog", "test_release_smoke.py", "scripts", "terracotta", ""], "setup": {"duration": 0.0002195920005760854, "outcome": "passed"}, "call": {"duration": 2.3567307650000657, "outcome": "passed"}, "teardown": {"duration": 8.161700043274323e-05, "outcome": "passed"}}, {"nodeid": "scripts/test_release_smoke.py::test_source_tree_version_strings", "lineno": 199, "outcome": "passed", "keywords": ["test_source_tree_version_strings", "test_release_smoke.py", "scripts", "terracotta", ""], "setup": {"duration": 0.00013691699950868497, "outcome": "passed"}, "call": {"duration": 2.054672313000083, "outcome": "passed"}, "teardown": {"duration": 0.0001426839999112417, "outcome": "passed"}}, {"nodeid": "scripts/test_release_smoke.py::test_gpg_signature_files", "lineno": 222, "outcome": "passed", "keywords": ["test_gpg_signature_files", "test_release_smoke.py", "scripts", "terracotta", ""], "setup": {"duration": 0.000284094000562618, "outcome": "passed"}, "call": {"duration": 0.3477014099998996, "outcome": "passed"}, "teardown": {"duration": 0.0002966459996969206, "outcome": "passed"}}, {"nodeid": "scripts/test_release_smoke.py::test_javadoc_jars_not_empty", "lineno": 272, "outcome": "passed", "keywords": ["test_javadoc_jars_not_empty", "test_release_smoke.py", "scripts", "terracotta", ""], "setup": {"duration": 0.0004848360003961716, "outcome": "passed"}, "call": {"duration": 0.2194118580000577, "outcome": "passed"}, "teardown": {"duration": 0.00011993599946436007, "outcome": "passed"}}, {"nodeid": "scripts/test_release_smoke.py::test_docs_sub_pages", "lineno": 300, "outcome": "failed", "keywords": ["test_docs_sub_pages", "test_release_smoke.py", "scripts", "terracotta", ""], "setup": {"duration": 0.00018561399974714732, "outcome": "passed"}, "call": {"duration": 0.5463088809992769, "outcome": "failed", "crash": {"path": "/home/luis/GitHub/beduality/terracotta/scripts/test_release_smoke.py", "lineno": 317, "message": "AssertionError: Docs sub-page failures: ['404 https://beduality.github.io/terracotta/0.3.0/content/sdk/reference/installation/', '404 https://beduality.github.io/terracotta/0.3.0/content/gradle-plugin/tutorials/getting-started/']\nassert not ['404 https://beduality.github.io/terracotta/0.3.0/content/sdk/reference/installation/', '404 https://beduality.github.io/terracotta/0.3.0/content/gradle-plugin/tutorials/getting-started/']"}, "traceback": [{"path": "scripts/test_release_smoke.py", "lineno": 317, "message": "AssertionError"}], "longrepr": "release_version = '0.3.0'\n\n    def test_docs_sub_pages(release_version):\n        \"\"\"Verify key docs pages return 200.\n    \n        MkDocs Material + mike deploys content under the version directory with a\n        `content/` prefix because the repo keeps source docs under `docs/content/`.\n        \"\"\"\n        paths = [\n            f\"https://beduality.github.io/terracotta/{release_version}/content/sdk/reference/installation/\",\n            f\"https://beduality.github.io/terracotta/{release_version}/content/gradle-plugin/tutorials/getting-started/\",\n            f\"https://beduality.github.io/terracotta/{release_version}/content/repo/how-to-guides/releasing/\",\n        ]\n        failures = []\n        for url in paths:\n            code = _http_code(url)\n            if code != 200:\n                failures.append(f\"{code} {url}\")\n>       assert not failures, f\"Docs sub-page failures: {failures}\"\nE       AssertionError: Docs sub-page failures: ['404 https://beduality.github.io/terracotta/0.3.0/content/sdk/reference/installation/', '404 https://beduality.github.io/terracotta/0.3.0/content/gradle-plugin/tutorials/getting-started/']\nE       assert not ['404 https://beduality.github.io/terracotta/0.3.0/content/sdk/reference/installation/', '404 https://beduality.github.io/terracotta/0.3.0/content/gradle-plugin/tutorials/getting-started/']\n\nscripts/test_release_smoke.py:317: AssertionError"}, "teardown": {"duration": 0.00010150800062547205, "outcome": "passed"}}, {"nodeid": "scripts/test_release_smoke.py::test_docs_version_reflected", "lineno": 319, "outcome": "passed", "keywords": ["test_docs_version_reflected", "test_release_smoke.py", "scripts", "terracotta", ""], "setup": {"duration": 0.00012250100007804576, "outcome": "passed"}, "call": {"duration": 0.19860160499956692, "outcome": "passed"}, "teardown": {"duration": 0.00035810899953503394, "outcome": "passed"}}, {"nodeid": "scripts/test_release_smoke.py::test_build_from_tag", "lineno": 331, "outcome": "failed", "keywords": ["test_build_from_tag", "skipif", "pytestmark", "test_release_smoke.py", "scripts", "terracotta", ""], "setup": {"duration": 0.0034752510000544135, "outcome": "passed"}, "call": {"duration": 13.272291747999589, "outcome": "failed", "crash": {"path": "/home/luis/.local/share/uv/python/cpython-3.13.9-linux-x86_64-gnu/lib/python3.13/subprocess.py", "lineno": 577, "message": "subprocess.CalledProcessError: Command '['./gradlew', 'spotlessCheck', 'build', '--no-daemon']' returned non-zero exit status 1."}, "traceback": [{"path": "scripts/test_release_smoke.py", "lineno": 338, "message": ""}, {"path": "scripts/test_release_smoke.py", "lineno": 52, "message": "in _run"}, {"path": "../../../.local/share/uv/python/cpython-3.13.9-linux-x86_64-gnu/lib/python3.13/subprocess.py", "lineno": 577, "message": "CalledProcessError"}], "longrepr": "release_version = '0.3.0', tag = 'v0.3.0'\n\n    @pytest.mark.skipif(\"not config.getoption('--build-from-tag')\")\n    def test_build_from_tag(release_version, tag):\n        repo_root = Path(__file__).resolve().parents[1]\n        _run([\"git\", \"fetch\", \"origin\", \"tag\", tag], cwd=repo_root, check=False)\n        _run([\"git\", \"checkout\", tag], cwd=repo_root)\n        try:\n>           result = _run([\"./gradlew\", \"spotlessCheck\", \"build\", \"--no-daemon\"], cwd=repo_root, timeout=300)\n                     ^^^^^^^^^^^^^^^^^^^^^^^^^^^^^^^^^^^^^^^^^^^^^^^^^^^^^^^^^^^^^^^^^^^^^^^^^^^^^^^^^^^^^^^^\n\nscripts/test_release_smoke.py:338: \n_ _ _ _ _ _ _ _ _ _ _ _ _ _ _ _ _ _ _ _ _ _ _ _ _ _ _ _ _ _ _ _ _ _ _ _ _ _ _ _ _ _ _ _ _ _ _ _ _ _ _ _ \nscripts/test_release_smoke.py:52: in _run\n    return subprocess.run(cmd, cwd=cwd, capture_output=True, text=True, check=check, timeout=timeout)\n           ^^^^^^^^^^^^^^^^^^^^^^^^^^^^^^^^^^^^^^^^^^^^^^^^^^^^^^^^^^^^^^^^^^^^^^^^^^^^^^^^^^^^^^^^^^\n_ _ _ _ _ _ _ _ _ _ _ _ _ _ _ _ _ _ _ _ _ _ _ _ _ _ _ _ _ _ _ _ _ _ _ _ _ _ _ _ _ _ _ _ _ _ _ _ _ _ _ _ \n\ninput = None, capture_output = True, timeout = 300, check = True\npopenargs = (['./gradlew', 'spotlessCheck', 'build', '--no-daemon'],)\nkwargs = {'cwd': PosixPath('/home/luis/GitHub/beduality/terracotta'), 'text': True, 'stdout': -1, 'stderr': -1}\n\n    def run(*popenargs,\n            input=None, capture_output=False, timeout=None, check=False, **kwargs):\n        \"\"\"Run command with arguments and return a CompletedProcess instance.\n    \n        The returned instance will have attributes args, returncode, stdout and\n        stderr. By default, stdout and stderr are not captured, and those attributes\n        will be None. Pass stdout=PIPE and/or stderr=PIPE in order to capture them,\n        or pass capture_output=True to capture both.\n    \n        If check is True and the exit code was non-zero, it raises a\n        CalledProcessError. The CalledProcessError object will have the return code\n        in the returncode attribute, and output & stderr attributes if those streams\n        were captured.\n    \n        If timeout (seconds) is given and the process takes too long,\n         a TimeoutExpired exception will be raised.\n    \n        There is an optional argument \"input\", allowing you to\n        pass bytes or a string to the subprocess's stdin.  If you use this argument\n        you may not also use the Popen constructor's \"stdin\" argument, as\n        it will be used internally.\n    \n        By default, all communication is in bytes, and therefore any \"input\" should\n        be bytes, and the stdout and stderr will be bytes. If in text mode, any\n        \"input\" should be a string, and stdout and stderr will be strings decoded\n        according to locale encoding, or by \"encoding\" if set. Text mode is\n        triggered by setting any of text, encoding, errors or universal_newlines.\n    \n        The other arguments are the same as for the Popen constructor.\n        \"\"\"\n        if input is not None:\n            if kwargs.get('stdin') is not None:\n                raise ValueError('stdin and input arguments may not both be used.')\n            kwargs['stdin'] = PIPE\n    \n        if capture_output:\n            if kwargs.get('stdout') is not None or kwargs.get('stderr') is not None:\n                raise ValueError('stdout and stderr arguments may not be used '\n                                 'with capture_output.')\n            kwargs['stdout'] = PIPE\n            kwargs['stderr'] = PIPE\n    \n        with Popen(*popenargs, **kwargs) as process:\n            try:\n                stdout, stderr = process.communicate(input, timeout=timeout)\n            except TimeoutExpired as exc:\n                process.kill()\n                if _mswindows:\n                    # Windows accumulates the output in a single blocking\n                    # read() call run on child threads, with the timeout\n                    # being done in a join() on those threads.  communicate()\n                    # _after_ kill() is required to collect that and add it\n                    # to the exception.\n                    exc.stdout, exc.stderr = process.communicate()\n                else:\n                    # POSIX _communicate already populated the output so\n                    # far into the TimeoutExpired exception.\n                    process.wait()\n                raise\n            except:  # Including KeyboardInterrupt, communicate handled that.\n                process.kill()\n                # We don't call process.wait() as .__exit__ does that for us.\n                raise\n            retcode = process.poll()\n            if check and retcode:\n>               raise CalledProcessError(retcode, process.args,\n                                         output=stdout, stderr=stderr)\nE               subprocess.CalledProcessError: Command '['./gradlew', 'spotlessCheck', 'build', '--no-daemon']' returned non-zero exit status 1.\n\n../../../.local/share/uv/python/cpython-3.13.9-linux-x86_64-gnu/lib/python3.13/subprocess.py:577: CalledProcessError"}, "teardown": {"duration": 0.0001253179998457199, "outcome": "passed"}}, {"nodeid": "scripts/test_release_smoke.py::test_gradle_plugin_e2e", "lineno": 343, "outcome": "passed", "keywords": ["test_gradle_plugin_e2e", "skipif", "pytestmark", "test_release_smoke.py", "scripts", "terracotta", ""], "setup": {"duration": 0.00019142099972668802, "outcome": "passed"}, "call": {"duration": 17.46810506299971, "outcome": "passed"}, "teardown": {"duration": 0.0007808410000507138, "outcome": "passed"}}, {"nodeid": "scripts/test_release_smoke.py::test_sdk_e2e", "lineno": 393, "outcome": "passed", "keywords": ["test_sdk_e2e", "skipif", "pytestmark", "test_release_smoke.py", "scripts", "terracotta", ""], "setup": {"duration": 0.0016141360001711291, "outcome": "passed"}, "call": {"duration": 17.256068183000025, "outcome": "passed"}, "teardown": {"duration": 0.00026600499950291123, "outcome": "passed"}}]}